CLEMENTS/Bunch.py
CLEMENTS/CLEMENT.py
CLEMENTS/EMhard.py
CLEMENTS/EMsoft.py
CLEMENTS/Estep.py
CLEMENTS/Mstep.py
CLEMENTS/__init__.py
CLEMENTS/comb.py
CLEMENTS/datapreparation.py
CLEMENTS/extract.py
CLEMENTS/filetype.py
CLEMENTS/graph.py
CLEMENTS/isparent.py
CLEMENTS/miscellaneous.py
CLEMENTS/phylogeny.py
CLEMENTS/result.py
CLEMENTS/setup.py
CLEMENTS/visualizationpair.py
CLEMENTS/visualizationpairsoft.py
CLEMENTS/visualizationsingle.py
CLEMENTS/visualizationsinglesoft.py
CLEMENTS-0.0.0.dist-info/METADATA
CLEMENTS-0.0.0.dist-info/WHEEL
CLEMENTS-0.0.0.dist-info/top_level.txt
CLEMENTS-0.0.0.dist-info/RECORD
