Metadata-Version: 2.1
Name: CLEMENTS
Version: 0.0.0
Summary: Genomic decomposition and reconstruction of non-tumor diploid subclones
Home-page: https://github.com/Yonsei-TGIL/CLEMENT
Author: Young-soo Chung, M.D.
Author-email: goldpm1@yuhs.ac
License: UNKNOWN
Download-URL: https://github.com/Yonsei-TGIL/CLEMENT.git
Keywords: CLEMENTS,genomic decomposition
Platform: UNKNOWN
Classifier: Programming Language :: Python :: 3.6
Requires-Python: >=3.6
Requires-Dist: matplotlib (>=3.5.2)
Requires-Dist: seaborn (>=0.11.2)
Requires-Dist: numpy (>=1.21.5)
Requires-Dist: pandas (>=1.3.4)
Requires-Dist: scikit-learn (>=1.0.2)
Requires-Dist: scipy (>=1.7.3)
Requires-Dist: palettable (>=3.3.0)
